{"title":"iPhone Theme Pinky by Lolote / iPod Touch Theme","uid":5427733,"size":3366609,"categoryP":"applications","categoryS":"handheld","magnet":"?xt=urn:btih:10d8bc83faf1c8c5253ef34f37d3728044c86a8f&amp;dn=iPhone+Theme+Pinky+by+Lolote+%2F+iPod+Touch+Theme&amp;tr=udp%3A%2F%2Ftracker.openbittorrent.com%3A80&amp;tr=udp%3A%2F%2Fopen.demonii.com%3A1337&amp;tr=udp%3A%2F%2Ftracker.coppersurfer.tk%3A6969&amp;tr=udp%3A%2F%2Fexodus.desync.com%3A6969","seeders":0,"leechers":0,"uploader":"Lolote123","files":-1,"time":1268308785,"description":"iPhone / iPod Touch Theme called Pinky.\n\n\n","torrent":{"xt":"urn:btih:10d8bc83faf1c8c5253ef34f37d3728044c86a8f","amp;dn":"iPhone+Theme+Pinky+by+Lolote+%2F+iPod+Touch+Theme","amp;tr":["udp%3A%2F%2Ftracker.openbittorrent.com%3A80","udp%3A%2F%2Fopen.demonii.com%3A1337","udp%3A%2F%2Ftracker.coppersurfer.tk%3A6969","udp%3A%2F%2Fexodus.desync.com%3A6969"],"infoHash":"10d8bc83faf1c8c5253ef34f37d3728044c86a8f","infoHashBuffer":{"type":"Buffer","data":[16,216,188,131,250,241,200,197,37,62,243,79,55,211,114,128,68,200,106,143]},"announce":[],"urlList":[]}}