{"title":"Saved games for Gothic 3","uid":3540245,"size":4812385,"categoryP":"games","categoryS":"other","magnet":"?xt=urn:btih:317e84316361dfa100f96b8d533a6a3121274ca0&amp;dn=Saved+games+for+Gothic+3&amp;tr=udp%3A%2F%2Ftracker.openbittorrent.com%3A80&amp;tr=udp%3A%2F%2Fopen.demonii.com%3A1337&amp;tr=udp%3A%2F%2Ftracker.coppersurfer.tk%3A6969&amp;tr=udp%3A%2F%2Fexodus.desync.com%3A6969","seeders":0,"leechers":0,"uploader":"Timich","files":1,"time":1160998876,"description":"Extract this archive to Gothic 3 savegame folder (default - &quot;...\\My documents\\gothic3&quot;)\nDefault language is English. To change game language, edit &quot;UserOptions.ini&quot;\n\nEnglish -&gt; German.\n\nVoiceLanguage=German\nSubtitleLanguage=German\n\nGerman -&gt; English\n\nVoiceLanguage=English\nSubtitleLanguage=English","torrent":{"xt":"urn:btih:317e84316361dfa100f96b8d533a6a3121274ca0","amp;dn":"Saved+games+for+Gothic+3","amp;tr":["udp%3A%2F%2Ftracker.openbittorrent.com%3A80","udp%3A%2F%2Fopen.demonii.com%3A1337","udp%3A%2F%2Ftracker.coppersurfer.tk%3A6969","udp%3A%2F%2Fexodus.desync.com%3A6969"],"infoHash":"317e84316361dfa100f96b8d533a6a3121274ca0","infoHashBuffer":{"type":"Buffer","data":[49,126,132,49,99,97,223,161,0,249,107,141,83,58,106,49,33,39,76,160]},"announce":[],"urlList":[]}}