{"title":"Red Riding Hood 2011 BRRip 720p x264 DXVA-MXMG","uid":6430745,"size":1565221052,"categoryP":"video","categoryS":"hd___movies","magnet":"?xt=urn:btih:34cae5c659087616b37feb6a3b928c991dfb1a4a&amp;dn=Red+Riding+Hood+2011+BRRip+720p+x264+DXVA-MXMG&amp;tr=udp%3A%2F%2Ftracker.openbittorrent.com%3A80&amp;tr=udp%3A%2F%2Fopen.demonii.com%3A1337&amp;tr=udp%3A%2F%2Ftracker.coppersurfer.tk%3A6969&amp;tr=udp%3A%2F%2Fexodus.desync.com%3A6969","seeders":0,"leechers":1,"uploader":"MXMG","files":4,"time":1306639402,"description":"[img]http://img189.imageshack.us/img189/1264/unled1nf.png[/img]\n\n\n[img]http://img861.imageshack.us/img861/4906/mxmgtorrentstate.jpg[/img]\n\n[img]http://img560.imageshack.us/img560/2197/redridinghoodmp4snapsho.png[/img]\n[img]http://img541.imageshack.us/img541/2197/redridinghoodmp4snapsho.png[/img]\n[img]http://img62.imageshack.us/img62/2197/redridinghoodmp4snapsho.png[/img]\n[img]http://img684.imageshack.us/img684/2197/redridinghoodmp4snapsho.png[/img]\n\n\n\n &lt;a href=&quot;\nhttp://www.chociz.com/&quot; rel=&quot;nofollow&quot; target=&quot;_NEW&quot;&gt;\nhttp://www.chociz.com/&lt;/a&gt;\n    Unlimited Bandwidth\n    Unlimited Torrents\n    ruTorrent webUI\n    Proxy &amp; Unrar Feature\n    Huge loads of Space\n\tEncrypted HTTP and FTP Access\n    100% Anonymous &amp; Secure\n\nNo setup fee, truly Unmetered Bandwidth !!\n\n\n\n\n\n\n","torrent":{"xt":"urn:btih:34cae5c659087616b37feb6a3b928c991dfb1a4a","amp;dn":"Red+Riding+Hood+2011+BRRip+720p+x264+DXVA-MXMG","amp;tr":["udp%3A%2F%2Ftracker.openbittorrent.com%3A80","udp%3A%2F%2Fopen.demonii.com%3A1337","udp%3A%2F%2Ftracker.coppersurfer.tk%3A6969","udp%3A%2F%2Fexodus.desync.com%3A6969"],"infoHash":"34cae5c659087616b37feb6a3b928c991dfb1a4a","infoHashBuffer":{"type":"Buffer","data":[52,202,229,198,89,8,118,22,179,127,235,106,59,146,140,153,29,251,26,74]},"announce":[],"urlList":[]}}