{"title":"[FakeAgentUK] Carla (E69) (14.03.2014)","uid":9767447,"size":978449176,"categoryP":"porn","categoryS":"movies","magnet":"?xt=urn:btih:3ce06790822f68c7618a7e60ad2c1d82cbf53bf8&amp;dn=%5BFakeAgentUK%5D+Carla+%28E69%29+%2814.03.2014%29&amp;tr=udp%3A%2F%2Ftracker.openbittorrent.com%3A80&amp;tr=udp%3A%2F%2Fopen.demonii.com%3A1337&amp;tr=udp%3A%2F%2Ftracker.coppersurfer.tk%3A6969&amp;tr=udp%3A%2F%2Fexodus.desync.com%3A6969","seeders":0,"leechers":1,"uploader":"xuluhulu","files":1,"time":1394902318,"description":"SCREENS:\n &lt;a href=&quot;\nhttp://www.imghoney.com/viewer.php?file=78337635188501628989.jpg&quot; rel=&quot;nofollow&quot; target=&quot;_NEW&quot;&gt;\nhttp://www.imghoney.com/viewer.php?file=78337635188501628989.jpg&lt;/a&gt;\n &lt;a href=&quot;\nhttp://www.imghoney.com/viewer.php?file=00148339744713845967.jpg&quot; rel=&quot;nofollow&quot; target=&quot;_NEW&quot;&gt;\nhttp://www.imghoney.com/viewer.php?file=00148339744713845967.jpg&lt;/a&gt;\n\n\nSEED &amp; ENJOY!!!","torrent":{"xt":"urn:btih:3ce06790822f68c7618a7e60ad2c1d82cbf53bf8","amp;dn":"%5BFakeAgentUK%5D+Carla+%28E69%29+%2814.03.2014%29","amp;tr":["udp%3A%2F%2Ftracker.openbittorrent.com%3A80","udp%3A%2F%2Fopen.demonii.com%3A1337","udp%3A%2F%2Ftracker.coppersurfer.tk%3A6969","udp%3A%2F%2Fexodus.desync.com%3A6969"],"infoHash":"3ce06790822f68c7618a7e60ad2c1d82cbf53bf8","infoHashBuffer":{"type":"Buffer","data":[60,224,103,144,130,47,104,199,97,138,126,96,173,44,29,130,203,245,59,248]},"announce":[],"urlList":[]}}