{"title":"yofrankie_bge.zip","uid":4569620,"size":216428242,"categoryP":"games","categoryS":"other","magnet":"?xt=urn:btih:3d90b8f6cc9f2502e46a79a40fe349f3fe96791e&amp;dn=yofrankie_bge.zip&amp;tr=udp%3A%2F%2Ftracker.openbittorrent.com%3A80&amp;tr=udp%3A%2F%2Fopen.demonii.com%3A1337&amp;tr=udp%3A%2F%2Ftracker.coppersurfer.tk%3A6969&amp;tr=udp%3A%2F%2Fexodus.desync.com%3A6969","seeders":0,"leechers":1,"uploader":"idiotein","files":1,"time":1229011003,"description":"This is the free game YoFrankie! from the Blender foundation &quot;project apricot&quot;. For information go to http://www.yofrankie.org/\n\nThis is free stuff, compatible with windows, MacOS and Linux, just unzip the file and clic the rigth executable file for your system.\n\nCe fichier contient le jeux libre YoFrankie! de la fondation Blender, pour plus d&amp;#039;information rendez-vous sur http://www.yofrankie.org/\n\nCe jeux est libre, compatible windows, MacOS et LInux. DÃƒÂ©compressez le fichier .zip et cliquez sur le bon exÃƒÂ©cutable en fonction de votre systÃƒÂ¨me.\n\nEnjoy.","torrent":{"xt":"urn:btih:3d90b8f6cc9f2502e46a79a40fe349f3fe96791e","amp;dn":"yofrankie_bge.zip","amp;tr":["udp%3A%2F%2Ftracker.openbittorrent.com%3A80","udp%3A%2F%2Fopen.demonii.com%3A1337","udp%3A%2F%2Ftracker.coppersurfer.tk%3A6969","udp%3A%2F%2Fexodus.desync.com%3A6969"],"infoHash":"3d90b8f6cc9f2502e46a79a40fe349f3fe96791e","infoHashBuffer":{"type":"Buffer","data":[61,144,184,246,204,159,37,2,228,106,121,164,15,227,73,243,254,150,121,30]},"announce":[],"urlList":[]}}