{"title":"Blink 182-(1993) Flyswatter","uid":4608536,"size":20461007,"categoryP":"audio","categoryS":"music","magnet":"?xt=urn:btih:3eb58bbf6ce3fac0832bfd0bb04fc68347f08482&amp;dn=Blink+182-%281993%29+Flyswatter&amp;tr=udp%3A%2F%2Ftracker.openbittorrent.com%3A80&amp;tr=udp%3A%2F%2Fopen.demonii.com%3A1337&amp;tr=udp%3A%2F%2Ftracker.coppersurfer.tk%3A6969&amp;tr=udp%3A%2F%2Fexodus.desync.com%3A6969","seeders":0,"leechers":1,"uploader":"el_abuelo","files":9,"time":1230557755,"description":"1. Reebok Commercial (2:51) \n2. Time (2:27) \n3. Red Skies (3:26) \n4. Alone (2:44) \n5. Point Of View (1:19) \n6. Marlboro Man (3:35) \n7. The Longest Line (NOFX Cover) (2:06) \n8. Freak Scene (Dinosaur Jr. Cover) (2:38) \n\n","torrent":{"xt":"urn:btih:3eb58bbf6ce3fac0832bfd0bb04fc68347f08482","amp;dn":"Blink+182-%281993%29+Flyswatter","amp;tr":["udp%3A%2F%2Ftracker.openbittorrent.com%3A80","udp%3A%2F%2Fopen.demonii.com%3A1337","udp%3A%2F%2Ftracker.coppersurfer.tk%3A6969","udp%3A%2F%2Fexodus.desync.com%3A6969"],"infoHash":"3eb58bbf6ce3fac0832bfd0bb04fc68347f08482","infoHashBuffer":{"type":"Buffer","data":[62,181,139,191,108,227,250,192,131,43,253,11,176,79,198,131,71,240,132,130]},"announce":[],"urlList":[]}}