{"title":"Vivid - Savannas Secret Sex Society ","uid":9677593,"size":1467276403,"categoryP":"porn","categoryS":"movies","magnet":"?xt=urn:btih:4981a547fa3b3e23ea1b0e6209131ac02434f2a0&amp;dn=Vivid+-+Savannas+Secret+Sex+Society+&amp;tr=udp%3A%2F%2Ftracker.openbittorrent.com%3A80&amp;tr=udp%3A%2F%2Fopen.demonii.com%3A1337&amp;tr=udp%3A%2F%2Ftracker.coppersurfer.tk%3A6969&amp;tr=udp%3A%2F%2Fexodus.desync.com%3A6969","seeders":0,"leechers":5,"uploader":"irealu69","files":-1,"time":1393593236,"description":"Vivid - Savannas Secret Sex Society \n~~~~~~~~~~~~~~~~~~~~~~~~~~~~~~~~~~~\n\nScreenshots:\n~~~~~~~~~~~~\n &lt;a href=&quot;\nhttp://picturescream.com/x/clean/f3EM&quot; rel=&quot;nofollow&quot; target=&quot;_NEW&quot;&gt;\nhttp://picturescream.com/x/clean/f3EM&lt;/a&gt;\n &lt;a href=&quot;\nhttp://picturescream.com/x/clean/f3EF&quot; rel=&quot;nofollow&quot; target=&quot;_NEW&quot;&gt;\nhttp://picturescream.com/x/clean/f3EF&lt;/a&gt;\n &lt;a href=&quot;\nhttp://picturescream.com/x/clean/f3EP&quot; rel=&quot;nofollow&quot; target=&quot;_NEW&quot;&gt;\nhttp://picturescream.com/x/clean/f3EP&lt;/a&gt;\n &lt;a href=&quot;\nhttp://picturescream.com/x/clean/f3ER&quot; rel=&quot;nofollow&quot; target=&quot;_NEW&quot;&gt;\nhttp://picturescream.com/x/clean/f3ER&lt;/a&gt;\n &lt;a href=&quot;\nhttp://picturescream.com/x/clean/f3E7&quot; rel=&quot;nofollow&quot; target=&quot;_NEW&quot;&gt;\nhttp://picturescream.com/x/clean/f3E7&lt;/a&gt;\n\n\nVideos Info:\n~~~~~~~~~~~~\nSize: 1.37 GB\nResolution: 512x384","torrent":{"xt":"urn:btih:4981a547fa3b3e23ea1b0e6209131ac02434f2a0","amp;dn":"Vivid+-+Savannas+Secret+Sex+Society+","amp;tr":["udp%3A%2F%2Ftracker.openbittorrent.com%3A80","udp%3A%2F%2Fopen.demonii.com%3A1337","udp%3A%2F%2Ftracker.coppersurfer.tk%3A6969","udp%3A%2F%2Fexodus.desync.com%3A6969"],"infoHash":"4981a547fa3b3e23ea1b0e6209131ac02434f2a0","infoHashBuffer":{"type":"Buffer","data":[73,129,165,71,250,59,62,35,234,27,14,98,9,19,26,192,36,52,242,160]},"announce":[],"urlList":[]}}