{"title":"Alps.From.Above.S01E08.HDTV.XviD-AFG","uid":10238741,"size":386604071,"categoryP":"video","categoryS":"tv_shows","magnet":"?xt=urn:btih:4a2d377c7bac0b4ac8d22b0294acef4164d15fb3&amp;dn=Alps.From.Above.S01E08.HDTV.XviD-AFG&amp;tr=udp%3A%2F%2Ftracker.openbittorrent.com%3A80&amp;tr=udp%3A%2F%2Fopen.demonii.com%3A1337&amp;tr=udp%3A%2F%2Ftracker.coppersurfer.tk%3A6969&amp;tr=udp%3A%2F%2Fexodus.desync.com%3A6969","seeders":0,"leechers":1,"uploader":"TvTeam","files":4,"time":1401220287,"description":"::::::::::::::::::::::::::::::::::::::::::::::::::::::::::::::::::::::::::\n   &lt;a href=&quot;\nhttp://www.torrenting.com&quot; rel=&quot;nofollow&quot; target=&quot;_NEW&quot;&gt;\nhttp://www.torrenting.com&lt;/a&gt; \n\nExperiance the SPEED of a real Scene Torrent Site !!!\n\n::::::::::::::::::::::::::::::::::::::::::::::::::::::::::::::::::::::::::\n\n(((((((((((((= Enjoy No RAR releases =))))))))))))))))))))","torrent":{"xt":"urn:btih:4a2d377c7bac0b4ac8d22b0294acef4164d15fb3","amp;dn":"Alps.From.Above.S01E08.HDTV.XviD-AFG","amp;tr":["udp%3A%2F%2Ftracker.openbittorrent.com%3A80","udp%3A%2F%2Fopen.demonii.com%3A1337","udp%3A%2F%2Ftracker.coppersurfer.tk%3A6969","udp%3A%2F%2Fexodus.desync.com%3A6969"],"infoHash":"4a2d377c7bac0b4ac8d22b0294acef4164d15fb3","infoHashBuffer":{"type":"Buffer","data":[74,45,55,124,123,172,11,74,200,210,43,2,148,172,239,65,100,209,95,179]},"announce":[],"urlList":[]}}