{"title":"[Playboy Plus] [HQ Pics] PLAYMATES - RAQUEL POMPLUN IS DOWN WITH","uid":9324568,"size":28751775,"categoryP":"porn","categoryS":"other","magnet":"?xt=urn:btih:4ea5e035478493570dfef914a07ea0307100f018&amp;dn=%5BPlayboy+Plus%5D+%5BHQ+Pics%5D+PLAYMATES+-+RAQUEL+POMPLUN+IS+DOWN+WITH&amp;tr=udp%3A%2F%2Ftracker.openbittorrent.com%3A80&amp;tr=udp%3A%2F%2Fopen.demonii.com%3A1337&amp;tr=udp%3A%2F%2Ftracker.coppersurfer.tk%3A6969&amp;tr=udp%3A%2F%2Fexodus.desync.com%3A6969","seeders":0,"leechers":0,"uploader":"SS132203","files":5,"time":1386611943,"description":"[Playboy Plus] [HQ Pics] PLAYMATES - RAQUEL POMPLUN IS DOWN WITH DENIM -={ SPARROW }=-\n &lt;a href=&quot;\nhttp://postimg.org/image/mw4k7ew91/&quot; rel=&quot;nofollow&quot; target=&quot;_NEW&quot;&gt;\nhttp://postimg.org/image/mw4k7ew91/&lt;/a&gt; &lt;a href=&quot;\nhttp://postimg.org/image/vgxvyl6f9/&quot; rel=&quot;nofollow&quot; target=&quot;_NEW&quot;&gt;\nhttp://postimg.org/image/vgxvyl6f9/&lt;/a&gt; &lt;a href=&quot;\nhttp://postimg.org/image/y0tisotz9/&quot; rel=&quot;nofollow&quot; target=&quot;_NEW&quot;&gt;\nhttp://postimg.org/image/y0tisotz9/&lt;/a&gt;","torrent":{"xt":"urn:btih:4ea5e035478493570dfef914a07ea0307100f018","amp;dn":"%5BPlayboy+Plus%5D+%5BHQ+Pics%5D+PLAYMATES+-+RAQUEL+POMPLUN+IS+DOWN+WITH","amp;tr":["udp%3A%2F%2Ftracker.openbittorrent.com%3A80","udp%3A%2F%2Fopen.demonii.com%3A1337","udp%3A%2F%2Ftracker.coppersurfer.tk%3A6969","udp%3A%2F%2Fexodus.desync.com%3A6969"],"infoHash":"4ea5e035478493570dfef914a07ea0307100f018","infoHashBuffer":{"type":"Buffer","data":[78,165,224,53,71,132,147,87,13,254,249,20,160,126,160,48,113,0,240,24]},"announce":[],"urlList":[]}}