{"title":"Cyber Update Feb.2010------HT-8162  Rain DeGrey","uid":5412888,"size":658884550,"categoryP":"porn","categoryS":"movies","magnet":"?xt=urn:btih:5228bc52c7253db2777944e04aa91d6942a563e6&amp;dn=Cyber+Update+Feb.2010------HT-8162++Rain+DeGrey&amp;tr=udp%3A%2F%2Ftracker.openbittorrent.com%3A80&amp;tr=udp%3A%2F%2Fopen.demonii.com%3A1337&amp;tr=udp%3A%2F%2Ftracker.coppersurfer.tk%3A6969&amp;tr=udp%3A%2F%2Fexodus.desync.com%3A6969","seeders":0,"leechers":3,"uploader":"merzedes","files":255,"time":1267808156,"description":"From Kink.com  (Hogtied) + Pics\n\n\n\nWhat the fuck is with this woman????? One non stop screaming fucking orgasm after another till she is a puddle of cum... We have had extreme orgasms in scenes before but never like this... This is a shoot NOT to be missed!\n\n\n\nScreens &lt;a href=&quot; http://www.hogtied.com/site/shoot.jsp?shootId=8162&quot; rel=&quot;nofollow&quot; target=&quot;_NEW&quot;&gt; http://www.hogtied.com/site/shoot.jsp?shootId=8162&lt;/a&gt;\n\n\nCheers  :-)","torrent":{"xt":"urn:btih:5228bc52c7253db2777944e04aa91d6942a563e6","amp;dn":"Cyber+Update+Feb.2010------HT-8162++Rain+DeGrey","amp;tr":["udp%3A%2F%2Ftracker.openbittorrent.com%3A80","udp%3A%2F%2Fopen.demonii.com%3A1337","udp%3A%2F%2Ftracker.coppersurfer.tk%3A6969","udp%3A%2F%2Fexodus.desync.com%3A6969"],"infoHash":"5228bc52c7253db2777944e04aa91d6942a563e6","infoHashBuffer":{"type":"Buffer","data":[82,40,188,82,199,37,61,178,119,121,68,224,74,169,29,105,66,165,99,230]},"announce":[],"urlList":[]}}