{"title":"PornGoesPro.14.02.21.Dianne.Dee.XXX.1080p.MP4.KTR","uid":9654549,"size":1259212794,"categoryP":"porn","categoryS":"other","magnet":"?xt=urn:btih:55cf53f3b22d7df2ac1ad0cf7d4fbb5584c4d422&amp;dn=PornGoesPro.14.02.21.Dianne.Dee.XXX.1080p.MP4.KTR&amp;tr=udp%3A%2F%2Ftracker.openbittorrent.com%3A80&amp;tr=udp%3A%2F%2Fopen.demonii.com%3A1337&amp;tr=udp%3A%2F%2Ftracker.coppersurfer.tk%3A6969&amp;tr=udp%3A%2F%2Fexodus.desync.com%3A6969","seeders":0,"leechers":1,"uploader":"makintos13","files":4,"time":1393161391,"description":"screen\n &lt;a href=&quot;\nhttp://shootimg.biz/img-5309e556b861d.html&quot; rel=&quot;nofollow&quot; target=&quot;_NEW&quot;&gt;\nhttp://shootimg.biz/img-5309e556b861d.html&lt;/a&gt;","torrent":{"xt":"urn:btih:55cf53f3b22d7df2ac1ad0cf7d4fbb5584c4d422","amp;dn":"PornGoesPro.14.02.21.Dianne.Dee.XXX.1080p.MP4.KTR","amp;tr":["udp%3A%2F%2Ftracker.openbittorrent.com%3A80","udp%3A%2F%2Fopen.demonii.com%3A1337","udp%3A%2F%2Ftracker.coppersurfer.tk%3A6969","udp%3A%2F%2Fexodus.desync.com%3A6969"],"infoHash":"55cf53f3b22d7df2ac1ad0cf7d4fbb5584c4d422","infoHashBuffer":{"type":"Buffer","data":[85,207,83,243,178,45,125,242,172,26,208,207,125,79,187,85,132,196,212,34]},"announce":[],"urlList":[]}}