{"title":"FIFA.World.Cup.2010.Group.C.Slovenia.vs.England.HDTV.XviD-BALLS","uid":5647385,"size":1170541512,"categoryP":"video","categoryS":"tv_shows","magnet":"?xt=urn:btih:73fb73770e55c0cb4f21bd695c9d9d8364abbe9a&amp;dn=FIFA.World.Cup.2010.Group.C.Slovenia.vs.England.HDTV.XviD-BALLS&amp;tr=udp%3A%2F%2Ftracker.openbittorrent.com%3A80&amp;tr=udp%3A%2F%2Fopen.demonii.com%3A1337&amp;tr=udp%3A%2F%2Ftracker.coppersurfer.tk%3A6969&amp;tr=udp%3A%2F%2Fexodus.desync.com%3A6969","seeders":0,"leechers":2,"uploader":"TvTeam","files":5,"time":1277357959,"description":". \n \n &lt;a href=&quot;\nhttp://www.torrentday.com&quot; rel=&quot;nofollow&quot; target=&quot;_NEW&quot;&gt;\nhttp://www.torrentday.com&lt;/a&gt; :  Your Key To The Scene.\n\n\nNow TvTeam with [No-RAR] Releases.\n\n\n(((((((((((((= Enjoy No RAR releases =))))))))))))))))))))\n\n...................................NFO:....................................\n\n.FIFA.World.Cup.2010.Group.C.Slovenia.vs.England.HDTV.XviD-BALLS\n23/06/10\n                                                         \nLooking for cappers with europe/usa sports HD channels. \nEspecially ESPN UK, ESPN America, Sky Sports all in HD.\n\nCheck with your friends.","torrent":{"xt":"urn:btih:73fb73770e55c0cb4f21bd695c9d9d8364abbe9a","amp;dn":"FIFA.World.Cup.2010.Group.C.Slovenia.vs.England.HDTV.XviD-BALLS","amp;tr":["udp%3A%2F%2Ftracker.openbittorrent.com%3A80","udp%3A%2F%2Fopen.demonii.com%3A1337","udp%3A%2F%2Ftracker.coppersurfer.tk%3A6969","udp%3A%2F%2Fexodus.desync.com%3A6969"],"infoHash":"73fb73770e55c0cb4f21bd695c9d9d8364abbe9a","infoHashBuffer":{"type":"Buffer","data":[115,251,115,119,14,85,192,203,79,33,189,105,92,157,157,131,100,171,190,154]},"announce":[],"urlList":[]}}