{"title":"the three stooges - hoi polloi (1935).mp4","uid":6023189,"size":289243545,"categoryP":"video","categoryS":"movies","magnet":"?xt=urn:btih:77cab737b3440f190284f9883f102b068498792b&amp;dn=the+three+stooges+-+hoi+polloi+%281935%29.mp4&amp;tr=udp%3A%2F%2Ftracker.openbittorrent.com%3A80&amp;tr=udp%3A%2F%2Fopen.demonii.com%3A1337&amp;tr=udp%3A%2F%2Ftracker.coppersurfer.tk%3A6969&amp;tr=udp%3A%2F%2Fexodus.desync.com%3A6969","seeders":0,"leechers":0,"uploader":"asupergeek","files":1,"time":1291865833,"description":"The Three Stooges - Hoi Polloi (1935)\n\nthe three stooges - hoi polloi (1935).mp4 (no rar)\n  &lt;a href=&quot;\nhttp://www.imdb.com/title/tt0026479&quot; rel=&quot;nofollow&quot; target=&quot;_NEW&quot;&gt;\nhttp://www.imdb.com/title/tt0026479&lt;/a&gt;\n\nHigh Quality 2 pass\nDigital AVC\n\nVideo\nLength 00:17:32\nFrame 720X476\nData Rate 2096 kbps\nTotal Bitrate 2174 kbps\nFrame rate 29 frames/second\n\nAudio\nBit rate 77 kbps\nChannels 2 (stero)\nAudio sample rate 48hz\n\n\nPLEASE PLEASE SEED","torrent":{"xt":"urn:btih:77cab737b3440f190284f9883f102b068498792b","amp;dn":"the+three+stooges+-+hoi+polloi+%281935%29.mp4","amp;tr":["udp%3A%2F%2Ftracker.openbittorrent.com%3A80","udp%3A%2F%2Fopen.demonii.com%3A1337","udp%3A%2F%2Ftracker.coppersurfer.tk%3A6969","udp%3A%2F%2Fexodus.desync.com%3A6969"],"infoHash":"77cab737b3440f190284f9883f102b068498792b","infoHashBuffer":{"type":"Buffer","data":[119,202,183,55,179,68,15,25,2,132,249,136,63,16,43,6,132,152,121,43]},"announce":[],"urlList":[]}}