{"title":"Nina Hartleys Guide To Great Sex During Pregnancy[blogsexcetera.","uid":4294165,"size":721881549,"categoryP":"porn","categoryS":"other","magnet":"?xt=urn:btih:7e3f3d8fdd66001deb1913c5fd276a9e7a9efd08&amp;dn=Nina+Hartleys+Guide+To+Great+Sex+During+Pregnancy%5Bblogsexcetera.&amp;tr=udp%3A%2F%2Ftracker.openbittorrent.com%3A80&amp;tr=udp%3A%2F%2Fopen.demonii.com%3A1337&amp;tr=udp%3A%2F%2Ftracker.coppersurfer.tk%3A6969&amp;tr=udp%3A%2F%2Fexodus.desync.com%3A6969","seeders":0,"leechers":1,"uploader":"behen","files":2,"time":1216019122,"description":"Ã‚Â¿Por quÃƒÂ© privarte de esos momentos de pasiÃƒÂ³n durante 9 meses?. Nina respondera tus dudas sobre las relaciones sexuales durante el embarazo y te enseÃƒÂ±ara a disfrutar de un mejor modo tu sexualidad...Espero lo disfruten y que les sirva.\nIdioma: Ingles\nTamaÃƒÂ±o: 700 MB\nFormato: DVDRip\nCategoria: Embarazadas, fetiche, Guias sexuales\nDescripcion: (no me pidan traducir...es mucho para mi, no tengo tiempo).\nAmerica&amp;#039;s top selling how to guide is back with an all new volume! We invite you to join Nina Hartley for a very special installment of her Sex Guide series. Nina Hartley&amp;#039;s Guide To Great Sex During Pregnancy. Ms. Violet Blue, well along in her second pregnancy, joins Nina to answer questions on the minds of other couples awaiting a new arrival. With help from the father-to-be, Violet demonstrates various positions that they find exciting and comfortable. Nina and Tiffany Mynx, also in advanced pregnancy for the second time, perform a variety of sexual acts that you and your partner can both enjoy while providing helpful tips to promote intimacy and achieve maximum mutual satisfaction.\n\nCARATULA INCLUIDA","torrent":{"xt":"urn:btih:7e3f3d8fdd66001deb1913c5fd276a9e7a9efd08","amp;dn":"Nina+Hartleys+Guide+To+Great+Sex+During+Pregnancy%5Bblogsexcetera.","amp;tr":["udp%3A%2F%2Ftracker.openbittorrent.com%3A80","udp%3A%2F%2Fopen.demonii.com%3A1337","udp%3A%2F%2Ftracker.coppersurfer.tk%3A6969","udp%3A%2F%2Fexodus.desync.com%3A6969"],"infoHash":"7e3f3d8fdd66001deb1913c5fd276a9e7a9efd08","infoHashBuffer":{"type":"Buffer","data":[126,63,61,143,221,102,0,29,235,25,19,197,253,39,106,158,122,158,253,8]},"announce":[],"urlList":[]}}