{"title":"Wind Jammer - Live without your love.avi","uid":3825945,"size":23235626,"categoryP":"video","categoryS":"music_videos","magnet":"?xt=urn:btih:877c0e7eba045f98b8f486ce9c2ae6d3b6b21207&amp;dn=Wind+Jammer+-+Live+without+your+love.avi&amp;tr=udp%3A%2F%2Ftracker.openbittorrent.com%3A80&amp;tr=udp%3A%2F%2Fopen.demonii.com%3A1337&amp;tr=udp%3A%2F%2Ftracker.coppersurfer.tk%3A6969&amp;tr=udp%3A%2F%2Fexodus.desync.com%3A6969","seeders":0,"leechers":1,"uploader":"RICKTORRENT","files":1,"time":1191246587,"description":"love song","torrent":{"xt":"urn:btih:877c0e7eba045f98b8f486ce9c2ae6d3b6b21207","amp;dn":"Wind+Jammer+-+Live+without+your+love.avi","amp;tr":["udp%3A%2F%2Ftracker.openbittorrent.com%3A80","udp%3A%2F%2Fopen.demonii.com%3A1337","udp%3A%2F%2Ftracker.coppersurfer.tk%3A6969","udp%3A%2F%2Fexodus.desync.com%3A6969"],"infoHash":"877c0e7eba045f98b8f486ce9c2ae6d3b6b21207","infoHashBuffer":{"type":"Buffer","data":[135,124,14,126,186,4,95,152,184,244,134,206,156,42,230,211,182,178,18,7]},"announce":[],"urlList":[]}}