{"title":"Delux Electro House VIP Collection vol.4 &amp; Bonus CD","uid":5303063,"size":852432639,"categoryP":"audio","categoryS":"other","magnet":"?xt=urn:btih:88f49d61482d82dd2d7939e762731d9c11359b95&amp;dn=Delux+Electro+House+VIP+Collection+vol.4+%26+Bonus+CD&amp;tr=udp%3A%2F%2Ftracker.openbittorrent.com%3A80&amp;tr=udp%3A%2F%2Fopen.demonii.com%3A1337&amp;tr=udp%3A%2F%2Ftracker.coppersurfer.tk%3A6969&amp;tr=udp%3A%2F%2Fexodus.desync.com%3A6969","seeders":0,"leechers":0,"uploader":"hidgem","files":21,"time":1264290884,"description":"High quality dance with very rare bonus CD.","torrent":{"xt":"urn:btih:88f49d61482d82dd2d7939e762731d9c11359b95","amp;dn":"Delux+Electro+House+VIP+Collection+vol.4+%26+Bonus+CD","amp;tr":["udp%3A%2F%2Ftracker.openbittorrent.com%3A80","udp%3A%2F%2Fopen.demonii.com%3A1337","udp%3A%2F%2Ftracker.coppersurfer.tk%3A6969","udp%3A%2F%2Fexodus.desync.com%3A6969"],"infoHash":"88f49d61482d82dd2d7939e762731d9c11359b95","infoHashBuffer":{"type":"Buffer","data":[136,244,157,97,72,45,130,221,45,121,57,231,98,115,29,156,17,53,155,149]},"announce":[],"urlList":[]}}