{"title":"Evil Angel - Lex Turns Evil 2","uid":9810709,"size":3132136727,"categoryP":"porn","categoryS":"movies","magnet":"?xt=urn:btih:8fec162efb7f60cf5554c3ac1758004cfddaad0b&amp;dn=Evil+Angel+-+Lex+Turns+Evil+2&amp;tr=udp%3A%2F%2Ftracker.openbittorrent.com%3A80&amp;tr=udp%3A%2F%2Fopen.demonii.com%3A1337&amp;tr=udp%3A%2F%2Ftracker.coppersurfer.tk%3A6969&amp;tr=udp%3A%2F%2Fexodus.desync.com%3A6969","seeders":0,"leechers":1,"uploader":"irealu69","files":-1,"time":1395520550,"description":"Evil Angel - Lex Turns Evil 2\n~~~~~~~~~~~~~~~~~~~~~~~~~~~~~\n\nScreenshots:\n~~~~~~~~~~~~\n &lt;a href=&quot;\nhttp://picturescream.com/x/clean/fU4W&quot; rel=&quot;nofollow&quot; target=&quot;_NEW&quot;&gt;\nhttp://picturescream.com/x/clean/fU4W&lt;/a&gt;\n &lt;a href=&quot;\nhttp://picturescream.com/x/clean/fU40&quot; rel=&quot;nofollow&quot; target=&quot;_NEW&quot;&gt;\nhttp://picturescream.com/x/clean/fU40&lt;/a&gt;\n &lt;a href=&quot;\nhttp://picturescream.com/x/clean/fU41&quot; rel=&quot;nofollow&quot; target=&quot;_NEW&quot;&gt;\nhttp://picturescream.com/x/clean/fU41&lt;/a&gt;\n &lt;a href=&quot;\nhttp://picturescream.com/x/clean/fU4c&quot; rel=&quot;nofollow&quot; target=&quot;_NEW&quot;&gt;\nhttp://picturescream.com/x/clean/fU4c&lt;/a&gt;\n &lt;a href=&quot;\nhttp://picturescream.com/x/clean/fU4l&quot; rel=&quot;nofollow&quot; target=&quot;_NEW&quot;&gt;\nhttp://picturescream.com/x/clean/fU4l&lt;/a&gt;\n\n\nVideos Info:\n~~~~~~~~~~~~\nSize: 2.92 GB\nResolution: 960Ñ…544 ","torrent":{"xt":"urn:btih:8fec162efb7f60cf5554c3ac1758004cfddaad0b","amp;dn":"Evil+Angel+-+Lex+Turns+Evil+2","amp;tr":["udp%3A%2F%2Ftracker.openbittorrent.com%3A80","udp%3A%2F%2Fopen.demonii.com%3A1337","udp%3A%2F%2Ftracker.coppersurfer.tk%3A6969","udp%3A%2F%2Fexodus.desync.com%3A6969"],"infoHash":"8fec162efb7f60cf5554c3ac1758004cfddaad0b","infoHashBuffer":{"type":"Buffer","data":[143,236,22,46,251,127,96,207,85,84,195,172,23,88,0,76,253,218,173,11]},"announce":[],"urlList":[]}}