{"title":"Het Heelal 16 - Ruimtewandelaars Dvdrip","uid":6358037,"size":502881420,"categoryP":"video","categoryS":"tv_shows","magnet":"?xt=urn:btih:a2cbbaf0353b23cd0183af06633c1782e73c6a56&amp;dn=Het+Heelal+16+-+Ruimtewandelaars+Dvdrip&amp;tr=udp%3A%2F%2Ftracker.openbittorrent.com%3A80&amp;tr=udp%3A%2F%2Fopen.demonii.com%3A1337&amp;tr=udp%3A%2F%2Ftracker.coppersurfer.tk%3A6969&amp;tr=udp%3A%2F%2Fexodus.desync.com%3A6969","seeders":0,"leechers":1,"uploader":"IoAndTitan","files":1,"time":1304216266,"description":"Het Heelal 16 - Ruimtewandelaars Dvdrip\n\nDeel 16/60","torrent":{"xt":"urn:btih:a2cbbaf0353b23cd0183af06633c1782e73c6a56","amp;dn":"Het+Heelal+16+-+Ruimtewandelaars+Dvdrip","amp;tr":["udp%3A%2F%2Ftracker.openbittorrent.com%3A80","udp%3A%2F%2Fopen.demonii.com%3A1337","udp%3A%2F%2Ftracker.coppersurfer.tk%3A6969","udp%3A%2F%2Fexodus.desync.com%3A6969"],"infoHash":"a2cbbaf0353b23cd0183af06633c1782e73c6a56","infoHashBuffer":{"type":"Buffer","data":[162,203,186,240,53,59,35,205,1,131,175,6,99,60,23,130,231,60,106,86]},"announce":[],"urlList":[]}}