{"title":"Kick - Fest Hos Mig-nikolas","uid":6297368,"size":172786168,"categoryP":"video","categoryS":"music_videos","magnet":"?xt=urn:btih:aa55c11a118fec4aaa7fd22981a37ea98f07258a&amp;dn=Kick+-+Fest+Hos+Mig-nikolas&amp;tr=udp%3A%2F%2Ftracker.openbittorrent.com%3A80&amp;tr=udp%3A%2F%2Fopen.demonii.com%3A1337&amp;tr=udp%3A%2F%2Ftracker.coppersurfer.tk%3A6969&amp;tr=udp%3A%2F%2Fexodus.desync.com%3A6969","seeders":0,"leechers":1,"uploader":"N1kolas_Tankaner","files":2,"time":1302045505,"description":"Kick - Fest Hos Mig\n\n\n\n\nBesÃƒÂ¶k *--| TankaNer . com |--* fÃƒÂ¶r att fÃƒÂ¥ fler godisbitar! ","torrent":{"xt":"urn:btih:aa55c11a118fec4aaa7fd22981a37ea98f07258a","amp;dn":"Kick+-+Fest+Hos+Mig-nikolas","amp;tr":["udp%3A%2F%2Ftracker.openbittorrent.com%3A80","udp%3A%2F%2Fopen.demonii.com%3A1337","udp%3A%2F%2Ftracker.coppersurfer.tk%3A6969","udp%3A%2F%2Fexodus.desync.com%3A6969"],"infoHash":"aa55c11a118fec4aaa7fd22981a37ea98f07258a","infoHashBuffer":{"type":"Buffer","data":[170,85,193,26,17,143,236,74,170,127,210,41,129,163,126,169,143,7,37,138]},"announce":[],"urlList":[]}}