{"title":"3D Sex Villa","uid":3601175,"size":10238959,"categoryP":"porn","categoryS":"games","magnet":"?xt=urn:btih:c20dbc73928a2b0aff85fbb119e72b0e404fbbab&amp;dn=3D+Sex+Villa&amp;tr=udp%3A%2F%2Ftracker.openbittorrent.com%3A80&amp;tr=udp%3A%2F%2Fopen.demonii.com%3A1337&amp;tr=udp%3A%2F%2Ftracker.coppersurfer.tk%3A6969&amp;tr=udp%3A%2F%2Fexodus.desync.com%3A6969","seeders":0,"leechers":1,"uploader":"gettattoo","files":1,"time":1169456273,"description":"Super sex simulator ;)","torrent":{"xt":"urn:btih:c20dbc73928a2b0aff85fbb119e72b0e404fbbab","amp;dn":"3D+Sex+Villa","amp;tr":["udp%3A%2F%2Ftracker.openbittorrent.com%3A80","udp%3A%2F%2Fopen.demonii.com%3A1337","udp%3A%2F%2Ftracker.coppersurfer.tk%3A6969","udp%3A%2F%2Fexodus.desync.com%3A6969"],"infoHash":"c20dbc73928a2b0aff85fbb119e72b0e404fbbab","infoHashBuffer":{"type":"Buffer","data":[194,13,188,115,146,138,43,10,255,133,251,177,25,231,43,14,64,79,187,171]},"announce":[],"urlList":[]}}