{"title":"WWE Monday Night Raw 08.09.2008 SDTV XviD-FWG","uid":4386582,"size":732482162,"categoryP":"video","categoryS":"tv_shows","magnet":"?xt=urn:btih:c677260077ccde2460bae3697a4286e8dc285da4&amp;dn=WWE+Monday+Night+Raw+08.09.2008+SDTV+XviD-FWG&amp;tr=udp%3A%2F%2Ftracker.openbittorrent.com%3A80&amp;tr=udp%3A%2F%2Fopen.demonii.com%3A1337&amp;tr=udp%3A%2F%2Ftracker.coppersurfer.tk%3A6969&amp;tr=udp%3A%2F%2Fexodus.desync.com%3A6969","seeders":0,"leechers":1,"uploader":"NEETIN","files":3,"time":1220947456,"description":"WWE Monday Night Raw 08.09.2008 SDTV XviD-FWG","torrent":{"xt":"urn:btih:c677260077ccde2460bae3697a4286e8dc285da4","amp;dn":"WWE+Monday+Night+Raw+08.09.2008+SDTV+XviD-FWG","amp;tr":["udp%3A%2F%2Ftracker.openbittorrent.com%3A80","udp%3A%2F%2Fopen.demonii.com%3A1337","udp%3A%2F%2Ftracker.coppersurfer.tk%3A6969","udp%3A%2F%2Fexodus.desync.com%3A6969"],"infoHash":"c677260077ccde2460bae3697a4286e8dc285da4","infoHashBuffer":{"type":"Buffer","data":[198,119,38,0,119,204,222,36,96,186,227,105,122,66,134,232,220,40,93,164]},"announce":[],"urlList":[]}}