{"title":"Tenderness.BRRIP.MP4.x264.720p-HR","uid":5316888,"size":2735696430,"categoryP":"video","categoryS":"hd___movies","magnet":"?xt=urn:btih:c9ae61655696cabe01004b392455b3eb635cd9e7&amp;dn=Tenderness.BRRIP.MP4.x264.720p-HR&amp;tr=udp%3A%2F%2Ftracker.openbittorrent.com%3A80&amp;tr=udp%3A%2F%2Fopen.demonii.com%3A1337&amp;tr=udp%3A%2F%2Ftracker.coppersurfer.tk%3A6969&amp;tr=udp%3A%2F%2Fexodus.desync.com%3A6969","seeders":0,"leechers":0,"uploader":"HolyRoses","files":-1,"time":1264744074,"description":"Source: Tenderness.LiMiTED.720p.BluRay.x264-ARiGOLD\n\nPoster: &lt;a href=&quot;\nhttp://img16.imageshack.us/img16/2048/tendernessposter.jpg&quot; rel=&quot;nofollow&quot; target=&quot;_NEW&quot;&gt;\nhttp://img16.imageshack.us/img16/2048/tendernessposter.jpg&lt;/a&gt;\n\nIcon: &lt;a href=&quot;\nhttp://bayimg.com/image/jakaoaaca.jpg&quot; rel=&quot;nofollow&quot; target=&quot;_NEW&quot;&gt;\nhttp://bayimg.com/image/jakaoaaca.jpg&lt;/a&gt;\n\nSnaps: &lt;a href=&quot;\nhttp://img718.imageshack.us/img718/3701/vlcsnap2010012819h40m38.png&quot; rel=&quot;nofollow&quot; target=&quot;_NEW&quot;&gt;\nhttp://img718.imageshack.us/img718/3701/vlcsnap2010012819h40m38.png&lt;/a&gt; &lt;a href=&quot;\nhttp://img52.imageshack.us/img52/7627/vlcsnap2010012819h41m42.png&quot; rel=&quot;nofollow&quot; target=&quot;_NEW&quot;&gt;\nhttp://img52.imageshack.us/img52/7627/vlcsnap2010012819h41m42.png&lt;/a&gt; &lt;a href=&quot;\nhttp://img6.imageshack.us/img6/6268/vlcsnap2010012819h42m03.png&quot; rel=&quot;nofollow&quot; target=&quot;_NEW&quot;&gt;\nhttp://img6.imageshack.us/img6/6268/vlcsnap2010012819h42m03.png&lt;/a&gt; &lt;a href=&quot;\nhttp://img42.imageshack.us/img42/361/vlcsnap2010012819h38m24.png&quot; rel=&quot;nofollow&quot; target=&quot;_NEW&quot;&gt;\nhttp://img42.imageshack.us/img42/361/vlcsnap2010012819h38m24.png&lt;/a&gt; &lt;a href=&quot;\nhttp://img52.imageshack.us/img52/1716/vlcsnap2010012819h38m54.png&quot; rel=&quot;nofollow&quot; target=&quot;_NEW&quot;&gt;\nhttp://img52.imageshack.us/img52/1716/vlcsnap2010012819h38m54.png&lt;/a&gt; &lt;a href=&quot;\nhttp://img6.imageshack.us/img6/2716/vlcsnap2010012819h39m18.png&quot; rel=&quot;nofollow&quot; target=&quot;_NEW&quot;&gt;\nhttp://img6.imageshack.us/img6/2716/vlcsnap2010012819h39m18.png&lt;/a&gt; &lt;a href=&quot;\nhttp://img52.imageshack.us/img52/2462/vlcsnap2010012819h39m37.png&quot; rel=&quot;nofollow&quot; target=&quot;_NEW&quot;&gt;\nhttp://img52.imageshack.us/img52/2462/vlcsnap2010012819h39m37.png&lt;/a&gt; &lt;a href=&quot;\nhttp://img52.imageshack.us/img52/6672/vlcsnap2010012819h40m08.png&quot; rel=&quot;nofollow&quot; target=&quot;_NEW&quot;&gt;\nhttp://img52.imageshack.us/img52/6672/vlcsnap2010012819h40m08.png&lt;/a&gt;\n\n-------------------------------------------------------\nDesigned for direct playback on Apple TV, PS3, WDTV, Xbox360, Popcorn Hour, VLC.\n\nWDTV users change extension from .m4v to .mp4\n\nApparently there is a sync problem with MP4 for WDTV Live with the latest firmware.\n\nIt is discussed here &lt;a href=&quot;\nhttp://wdtvhd.com/index.php?showtopic=8778&quot; rel=&quot;nofollow&quot; target=&quot;_NEW&quot;&gt;\nhttp://wdtvhd.com/index.php?showtopic=8778&lt;/a&gt;\nand here &lt;a href=&quot;\nhttp://community.wdc.com/t5/WD-TV-Live-Firmware/1-0-17-MP4-Audio-Sync/td-p/6146&quot; rel=&quot;nofollow&quot; target=&quot;_NEW&quot;&gt;\nhttp://community.wdc.com/t5/WD-TV-Live-Firmware/1-0-17-MP4-Audio-Sync/td-p/6146&lt;/a&gt;\nand suggested to rollback firmware to revision 1.01.00\n\nApple TV user ensure running firmware 3.0.1  Use custom iTunes movie sync option &quot;Automatically include the 10 most recent movies along with selected movies.&quot;\n--------------------------------------------------------\nVideo technical specifications:\n\nVideo:\nCodec: AVC via x264\nProfile: &lt;a class=&quot;__cf_email__&quot; href=&quot;/cdn-cgi/l/email-protection&quot; data-cfemail=&quot;226a4b454a62110c13&quot;&gt;[email&amp;#160;protected]&lt;/a&gt;&lt;script cf-hash='f9e31' type=&quot;text/javascript&quot;&gt;\n/* &lt;![CDATA[ */!function(){try{var t=&quot;currentScript&quot;in document?document.currentScript:function(){for(var t=document.getElementsByTagName(&quot;script&quot;),e=t.length;e--;)if(t[e].getAttribute(&quot;cf-hash&quot;))return t[e]}();if(t&amp;&amp;t.previousSibling){var e,r,n,i,c=t.previousSibling,a=c.getAttribute(&quot;data-cfemail&quot;);if(a){for(e=&quot;&quot;,r=parseInt(a.substr(0,2),16),n=2;a.length-n;n+=2)i=parseInt(a.substr(n,2),16)^r,e+=String.fromCharCode(i);e=document.createTextNode(e),c.parentNode.replaceChild(e,c)}}}catch(u){}}();/* ]]&gt; */&lt;/script&gt;\nBitrate: 3072 Kbps\nFPS: 23.976\nRate Control: 2 pass\n\nAudio 1:\nCodec: AAC Stereo\nBitrate: 160 Kbps\n(for everything)\n\nAudio 2:\nCodec: Dolby Digital 5.1\nBitrate: 384 Kbps\n(for Apple TV use TOSLINK to receiver to enable DD, or use WDTV Live, or VLC on PC)\n\nSubtitle 1:\nEnglish\n-------------------------------------------------------\n\n-HR\n","torrent":{"xt":"urn:btih:c9ae61655696cabe01004b392455b3eb635cd9e7","amp;dn":"Tenderness.BRRIP.MP4.x264.720p-HR","amp;tr":["udp%3A%2F%2Ftracker.openbittorrent.com%3A80","udp%3A%2F%2Fopen.demonii.com%3A1337","udp%3A%2F%2Ftracker.coppersurfer.tk%3A6969","udp%3A%2F%2Fexodus.desync.com%3A6969"],"infoHash":"c9ae61655696cabe01004b392455b3eb635cd9e7","infoHashBuffer":{"type":"Buffer","data":[201,174,97,101,86,150,202,190,1,0,75,57,36,85,179,235,99,92,217,231]},"announce":[],"urlList":[]}}