{"title":"DoomSword -2011- The Eternal Battle","uid":6201622,"size":92489830,"categoryP":"audio","categoryS":"music","magnet":"?xt=urn:btih:dff226d4b41f420fa91a93ef8cf88cd4cb710cec&amp;dn=DoomSword+-2011-+The+Eternal+Battle&amp;tr=udp%3A%2F%2Ftracker.openbittorrent.com%3A80&amp;tr=udp%3A%2F%2Fopen.demonii.com%3A1337&amp;tr=udp%3A%2F%2Ftracker.coppersurfer.tk%3A6969&amp;tr=udp%3A%2F%2Fexodus.desync.com%3A6969","seeders":0,"leechers":0,"uploader":"UGATeam","files":9,"time":1298639560,"description":" Downloaded from Rockbox.If you like this,support the band \nbuy the cd.Also seed it as much you can.","torrent":{"xt":"urn:btih:dff226d4b41f420fa91a93ef8cf88cd4cb710cec","amp;dn":"DoomSword+-2011-+The+Eternal+Battle","amp;tr":["udp%3A%2F%2Ftracker.openbittorrent.com%3A80","udp%3A%2F%2Fopen.demonii.com%3A1337","udp%3A%2F%2Ftracker.coppersurfer.tk%3A6969","udp%3A%2F%2Fexodus.desync.com%3A6969"],"infoHash":"dff226d4b41f420fa91a93ef8cf88cd4cb710cec","infoHashBuffer":{"type":"Buffer","data":[223,242,38,212,180,31,66,15,169,26,147,239,140,248,140,212,203,113,12,236]},"announce":[],"urlList":[]}}