{"title":"Shane Diesel's Breakin' Em In Young 1 (Jonalungus, Bone Digital ","uid":9159958,"size":2142175232,"categoryP":"porn","categoryS":"movies","magnet":"?xt=urn:btih:e160061791e0ac16c48844a2c8176e89b18e1142&amp;dn=Shane+Diesel%27s+Breakin%27+Em+In+Young+1+%28Jonalungus%2C+Bone+Digital+&amp;tr=udp%3A%2F%2Ftracker.openbittorrent.com%3A80&amp;tr=udp%3A%2F%2Fopen.demonii.com%3A1337&amp;tr=udp%3A%2F%2Ftracker.coppersurfer.tk%3A6969&amp;tr=udp%3A%2F%2Fexodus.desync.com%3A6969","seeders":0,"leechers":3,"uploader":"SplashPt","files":1,"time":1383857827,"description":"Shane Diesel's Breakin' Em In Young 1 (Jonalungus, Bone Digital / 2007)\n\nLooks like she traded in her pom poms for some cock!!! Fuck school, she needs some dick!! her vertical smile just took the black mile!! It's the black vein of pain!!! Try reading with that in your mouth!!! Its an all out slaughter on your daughter . I went out shopping and all i got was the big black dick !! Holy shit!! Now that's what i call gettting fucked!!!\n\nBrianna Love, Shane Diesel, Megan Monroe, Haileey James, Nadia Nitro, Nka\n\nBig Dicks, Legal Teen, BlowJobs, Interracial, Hardcore, All Sex\n\nScreens:\n &lt;a href=&quot;\nhttp://www.244pix.com/viewer.php?file=720z8ueih2eg.jpg&quot; rel=&quot;nofollow&quot; target=&quot;_NEW&quot;&gt;\nhttp://www.244pix.com/viewer.php?file=720z8ueih2eg.jpg&lt;/a&gt;\n &lt;a href=&quot;\nhttp://www.244pix.com/viewer.php?file=7iwxthk4ox0d.jpg&quot; rel=&quot;nofollow&quot; target=&quot;_NEW&quot;&gt;\nhttp://www.244pix.com/viewer.php?file=7iwxthk4ox0d.jpg&lt;/a&gt;","torrent":{"xt":"urn:btih:e160061791e0ac16c48844a2c8176e89b18e1142","amp;dn":"Shane+Diesel%27s+Breakin%27+Em+In+Young+1+%28Jonalungus%2C+Bone+Digital+","amp;tr":["udp%3A%2F%2Ftracker.openbittorrent.com%3A80","udp%3A%2F%2Fopen.demonii.com%3A1337","udp%3A%2F%2Ftracker.coppersurfer.tk%3A6969","udp%3A%2F%2Fexodus.desync.com%3A6969"],"infoHash":"e160061791e0ac16c48844a2c8176e89b18e1142","infoHashBuffer":{"type":"Buffer","data":[225,96,6,23,145,224,172,22,196,136,68,162,200,23,110,137,177,142,17,66]},"announce":[],"urlList":[]}}