{"title":"Operation.Mincemeat.WS.PDTV.XviD-FTP","uid":6014742,"size":575974362,"categoryP":"video","categoryS":"tv_shows","magnet":"?xt=urn:btih:ed946051a4c96c79b39feabf30590bb39eca8c79&amp;dn=Operation.Mincemeat.WS.PDTV.XviD-FTP&amp;tr=udp%3A%2F%2Ftracker.openbittorrent.com%3A80&amp;tr=udp%3A%2F%2Fopen.demonii.com%3A1337&amp;tr=udp%3A%2F%2Ftracker.coppersurfer.tk%3A6969&amp;tr=udp%3A%2F%2Fexodus.desync.com%3A6969","seeders":0,"leechers":1,"uploader":"TvTeam","files":3,"time":1291594289,"description":". \n  &lt;a href=&quot;\nhttp://www.torrentday.com/&quot; rel=&quot;nofollow&quot; target=&quot;_NEW&quot;&gt;\nhttp://www.torrentday.com/&lt;/a&gt;        :     The Hottest Private Tracker On The Net!!!\n\n\nTo Avoid Fakes, ALWAYS Check That The Torrent Was Added By: TvTeam.\n\n\n               www . TorrentDay . Com \n(((((((((((((= Enjoy No RAR releases =))))))))))))))))))))\n\n...................................NFO:....................................\n\n.","torrent":{"xt":"urn:btih:ed946051a4c96c79b39feabf30590bb39eca8c79","amp;dn":"Operation.Mincemeat.WS.PDTV.XviD-FTP","amp;tr":["udp%3A%2F%2Ftracker.openbittorrent.com%3A80","udp%3A%2F%2Fopen.demonii.com%3A1337","udp%3A%2F%2Ftracker.coppersurfer.tk%3A6969","udp%3A%2F%2Fexodus.desync.com%3A6969"],"infoHash":"ed946051a4c96c79b39feabf30590bb39eca8c79","infoHashBuffer":{"type":"Buffer","data":[237,148,96,81,164,201,108,121,179,159,234,191,48,89,11,179,158,202,140,121]},"announce":[],"urlList":[]}}