{"title":"Jack.Taylor.S01E02.Auge.um.Auge.German.WS.HDTV.x264-CNHD","uid":9165337,"size":738367872,"categoryP":"video","categoryS":"tv_shows","magnet":"?xt=urn:btih:fc0f64992c630a118614d3fa9eb1162d2dd51705&amp;dn=Jack.Taylor.S01E02.Auge.um.Auge.German.WS.HDTV.x264-CNHD&amp;tr=udp%3A%2F%2Ftracker.openbittorrent.com%3A80&amp;tr=udp%3A%2F%2Fopen.demonii.com%3A1337&amp;tr=udp%3A%2F%2Ftracker.coppersurfer.tk%3A6969&amp;tr=udp%3A%2F%2Fexodus.desync.com%3A6969","seeders":0,"leechers":1,"uploader":"TvTeam","files":5,"time":1383968004,"description":"::::::::::::::::::::::::::::::::::::::::::::::::::::::::::::::::::::::::::\n &lt;a href=&quot;\nhttp://www.torrenting.com&quot; rel=&quot;nofollow&quot; target=&quot;_NEW&quot;&gt;\nhttp://www.torrenting.com&lt;/a&gt;\n\nEver Experianced a perfect Scene torrent site?\n\n\n\nGive it a try: http://www.torrenting.com\n\n\n\nYou will not regret.\n\nSign up is free and open !!!\n\n\n::::::::::::::::::::::::::::::::::::::::::::::::::::::::::::::::::::::::::\n\n(= Enjoy No RAR releases =)","torrent":{"xt":"urn:btih:fc0f64992c630a118614d3fa9eb1162d2dd51705","amp;dn":"Jack.Taylor.S01E02.Auge.um.Auge.German.WS.HDTV.x264-CNHD","amp;tr":["udp%3A%2F%2Ftracker.openbittorrent.com%3A80","udp%3A%2F%2Fopen.demonii.com%3A1337","udp%3A%2F%2Ftracker.coppersurfer.tk%3A6969","udp%3A%2F%2Fexodus.desync.com%3A6969"],"infoHash":"fc0f64992c630a118614d3fa9eb1162d2dd51705","infoHashBuffer":{"type":"Buffer","data":[252,15,100,153,44,99,10,17,134,20,211,250,158,177,22,45,45,213,23,5]},"announce":[],"urlList":[]}}